lyric_py_worker/__init__.py
lyric_py_worker/python_worker.wasm
lyric_py_worker-0.1.7.dist-info/METADATA
lyric_py_worker-0.1.7.dist-info/WHEEL
lyric_py_worker-0.1.7.dist-info/RECORD
